viv_utils/__init__.py
viv_utils/emulator_drivers.py
viv_utils/flirt.py
viv_utils/idaloader.py
viv_utils/types.py
viv_utils/scripts/__init__.py
viv_utils/scripts/get_flirt_matches.py
viv_utils/scripts/get_function_args.py
viv_utils/scripts/show_flirt_references.py
viv_utils/scripts/trace_function_emulation.py
viv_utils-0.7.13.dist-info/LICENSE
viv_utils-0.7.13.dist-info/METADATA
viv_utils-0.7.13.dist-info/WHEEL
viv_utils-0.7.13.dist-info/top_level.txt
viv_utils-0.7.13.dist-info/RECORD
