Metadata-Version: 2.1
Name: viv_utils
Version: 0.7.13
Summary: Utilities for binary analysis using vivisect.
Author-email: Willi Ballenthin <william.ballenthin@mandiant.com>, Moritz Raabe <moritz.raabe@mandiant.com>
License: Apache License
Project-URL: Homepage, https://github.com/williballenthin/viv-utils
Project-URL: Repository, https://github.com/williballenthin/viv-utils.git
Keywords: malware analysis,reverse engineering,emulation,disassembly
Classifier: Development Status :: 5 - Production/Stable
Classifier: Intended Audience :: Developers
Classifier: Intended Audience :: Information Technology
Classifier: License :: OSI Approved :: Apache Software License
Classifier: Natural Language :: English
Classifier: Programming Language :: Python :: 3
Classifier: Topic :: Security
Requires-Python: >=3.8
License-File: LICENSE
Requires-Dist: funcy >=2.0
Requires-Dist: pefile >=2023.2.7
Requires-Dist: vivisect >=1.1.0
Requires-Dist: intervaltree >=3.1.0
Requires-Dist: typing-extensions >=4.5.0
Provides-Extra: build
Requires-Dist: setuptools ==75.2.0 ; extra == 'build'
Requires-Dist: build ==1.2.1 ; extra == 'build'
Provides-Extra: dev
Requires-Dist: pytest ==8.2.2 ; extra == 'dev'
Requires-Dist: pytest-sugar ==1.0.0 ; extra == 'dev'
Requires-Dist: pytest-instafail ==0.5.0 ; extra == 'dev'
Requires-Dist: pycodestyle ==2.12.0 ; extra == 'dev'
Requires-Dist: black ==24.4.2 ; extra == 'dev'
Requires-Dist: isort ==5.13.2 ; extra == 'dev'
Requires-Dist: mypy ==1.11.2 ; extra == 'dev'
Requires-Dist: types-setuptools ==75.2.0.20241019 ; extra == 'dev'
Provides-Extra: flirt
Requires-Dist: python-flirt ==0.9.0 ; extra == 'flirt'
